speedtools/__init__.py
speedtools/cam_data.py
speedtools/can_data.py
speedtools/carp_data.py
speedtools/frd_data.py
speedtools/fsh_data.py
speedtools/refpack.py
speedtools/speedtool.py
speedtools/tr_ini.py
speedtools/track_data.py
speedtools/types.py
speedtools/utils.py
speedtools/viv_data.py
speedtools/blender/__init__.py
speedtools/blender/io_nfs4_import.py
speedtools/parsers/__init__.py
speedtools/parsers/cam.py
speedtools/parsers/can.py
speedtools/parsers/fce.py
speedtools/parsers/frd.py
speedtools/parsers/fsh.py
speedtools/parsers/qfs.py
speedtools/parsers/sim.py
speedtools/parsers/viv.py
speedtools/specs/cam.ksy
speedtools/specs/can.ksy
speedtools/specs/fce.ksy
speedtools/specs/frd.ksy
speedtools/specs/fsh.ksy
speedtools/specs/heights_sim.ksy
speedtools/specs/qfs.ksy
speedtools/specs/viv.ksy
speedtools-0.26.0.dist-info/licenses/LICENSE
speedtools-0.26.0.dist-info/METADATA
speedtools-0.26.0.dist-info/WHEEL
speedtools-0.26.0.dist-info/entry_points.txt
speedtools-0.26.0.dist-info/top_level.txt
speedtools-0.26.0.dist-info/RECORD
