Metadata-Version: 2.4
Name: speedtools
Version: 0.26.0
Summary: NFS4 HS (PC) resource utilities
Author: Rafał Kuźnia
Author-email: rafal.kuznia@protonmail.com
License: GPL-3.0-or-later
Project-URL: homepage, https://github.com/e-rk/speedtools
Project-URL: repository, https://github.com/e-rk/speedtools
Classifier: License :: OSI Approved :: GNU General Public License v3 or later (GPLv3+)
Classifier: Operating System :: OS Independent
Classifier: Programming Language :: Python
Classifier: Programming Language :: Python :: 3
Classifier: Programming Language :: Python :: 3.10
Classifier: Programming Language :: Python :: 3.11
Classifier: Programming Language :: Python :: 3 :: Only
Classifier: Topic :: File Formats
Classifier: Typing :: Typed
License-File: LICENSE
Requires-Dist: kaitaistruct
Requires-Dist: pillow
Requires-Dist: click
Requires-Dist: more-itertools
Requires-Dist: parse
Dynamic: license-file
